<?xml version="1.0" encoding="utf-8"?>
<!DOCTYPE hibernate-mapping PUBLIC "-//Hibernate/Hibernate Mapping DTD 3.0//EN"
"http://www.hibernate.org/dtd/hibernate-mapping-3.0.dtd">
<!-- 
    Mapping file autogenerated by MyEclipse Persistence Tools
-->
<hibernate-mapping>
    <class name="com.zj198.model.AdsPost" table="ADS_POST">
        <id name="id" type="java.lang.Integer">
            <column name="ID" />
            <generator class="identity" />
        </id>
        <property name="startdate" type="java.util.Date">
            <column name="STARTDATE" length="10" not-null="true">
                <comment>开始日期</comment>
            </column>
        </property>
        <property name="enddate" type="java.util.Date">
            <column name="ENDDATE" length="10" not-null="true">
                <comment>结束日期</comment>
            </column>
        </property>
        <property name="status" type="java.lang.Integer">
            <column name="STATUS" not-null="true">
                <comment>状态0正常 1停止</comment>
            </column>
        </property>
        <property name="placeid" type="java.lang.Integer">
            <column name="PLACEID" not-null="true">
                <comment>广告位</comment>
            </column>
        </property>
        <property name="itemids" type="java.lang.String">
            <column name="ITEMIDS" length="45" not-null="true">
                <comment>广告项们</comment>
            </column>
        </property>
    </class>
</hibernate-mapping>
