{"name":"html","children":[{"name":"head","children":[{"name":"meta"},{"name":"meta"},{"name":"mata","children":[{"name":"meta"},{"name":"title","children":[{"name":"data"}]},{"name":"link"},{"name":"link"},{"name":"link"}]}]},{"name":"body","children":[{"name":"div","children":[{"name":"a","children":[{"name":"img"}]},{"name":"a","children":[{"name":"img"}]},{"name":"div","children":[{"name":"ul","children":[{"name":"li","children":[{"name":"a","children":[{"name":"data"}]}]},{"name":"li","children":[{"name":"data"}]},{"name":"li","children":[{"name":"a","children":[{"name":"data"}]}]},{"name":"li","children":[{"name":"data"}]},{"name":"li","children":[{"name":"a","children":[{"name":"data"}]}]},{"name":"li","children":[{"name":"data"}]},{"name":"li","children":[{"name":"a","children":[{"name":"data"}]}]},{"name":"li","children":[{"name":"data"}]},{"name":"li","children":[{"name":"a","children":[{"name":"data"}]}]},{"name":"li","children":[{"name":"data"}]},{"name":"li","children":[{"name":"a","children":[{"name":"data"}]}]},{"name":"li","children":[{"name":"data"}]},{"name":"li","children":[{"name":"a","children":[{"name":"data"}]}]},{"name":"li","children":[{"name":"data"}]},{"name":"li","children":[{"name":"a","children":[{"name":"data"}]}]},{"name":"li","children":[{"name":"data"}]},{"name":"li","children":[{"name":"a","children":[{"name":"data"}]}]},{"name":"li","children":[{"name":"data"}]},{"name":"li","children":[{"name":"a","children":[{"name":"data"}]}]},{"name":"li","children":[{"name":"data"}]},{"name":"li","children":[{"name":"a","children":[{"name":"data"}]}]},{"name":"li","children":[{"name":"data"}]},{"name":"li","children":[{"name":"a","children":[{"name":"data"}]}]},{"name":"li","children":[{"name":"data"}]},{"name":"li","children":[{"name":"a","children":[{"name":"data"}]}]},{"name":"li","children":[{"name":"data"}]},{"name":"li","children":[{"name":"a","children":[{"name":"data"}]}]},{"name":"li","children":[{"name":"data"}]},{"name":"li","children":[{"name":"a","children":[{"name":"data"}]}]},{"name":"li","children":[{"name":"data"}]},{"name":"li","children":[{"name":"a","children":[{"name":"data"}]}]},{"name":"li","children":[{"name":"data"}]},{"name":"li","children":[{"name":"a","children":[{"name":"data"}]}]},{"name":"li","children":[{"name":"data"}]},{"name":"li","children":[{"name":"a","children":[{"name":"data"}]}]},{"name":"li","children":[{"name":"data"}]},{"name":"li","children":[{"name":"a","children":[{"name":"data"}]}]},{"name":"li","children":[{"name":"data"}]},{"name":"li","children":[{"name":"a","children":[{"name":"data"}]}]}]}]}]},{"name":"div","children":[{"name":"div","children":[{"name":"a","children":[{"name":"img"}]},{"name":"div","children":[{"name":"p","children":[{"name":"a","children":[{"name":"data"}]},{"name":"data"},{"name":"a","children":[{"name":"data"}]}]},{"name":"p","children":[{"name":"a","children":[{"name":"data"}]},{"name":"data"},{"name":"a","children":[{"name":"data"}]}]}]}]},{"name":"div","children":[{"name":"a","children":[{"name":"img"}]},{"name":"div","children":[{"name":"p","children":[{"name":"a","children":[{"name":"data"}]},{"name":"data"},{"name":"a","children":[{"name":"data"}]}]},{"name":"p","children":[{"name":"a","children":[{"name":"font","children":[{"name":"data"}]}]},{"name":"data"},{"name":"a","children":[{"name":"data"}]}]}]}]},{"name":"div","children":[{"name":"a","children":[{"name":"img"}]},{"name":"div","children":[{"name":"p","children":[{"name":"a","children":[{"name":"data"}]},{"name":"data"},{"name":"a","children":[{"name":"data"}]},{"name":"data"},{"name":"a","children":[{"name":"data"}]},{"name":"data"},{"name":"a","children":[{"name":"data"}]},{"name":"data"},{"name":"a","children":[{"name":"data"}]},{"name":"data"},{"name":"a","children":[{"name":"data"}]},{"name":"data"},{"name":"a","children":[{"name":"data"}]},{"name":"data"},{"name":"a","children":[{"name":"data"}]},{"name":"data"},{"name":"a","children":[{"name":"data"}]}]},{"name":"p","children":[{"name":"a","children":[{"name":"data"}]},{"name":"data"},{"name":"a","children":[{"name":"data"}]},{"name":"data"},{"name":"a","children":[{"name":"data"}]},{"name":"data"},{"name":"a","children":[{"name":"data"}]},{"name":"data"},{"name":"a","children":[{"name":"data"}]},{"name":"data"},{"name":"a","children":[{"name":"data"}]},{"name":"data"},{"name":"a","children":[{"name":"data"}]},{"name":"data"},{"name":"a","children":[{"name":"data"}]},{"name":"data"},{"name":"a","children":[{"name":"data"}]}]}]}]},{"name":"div","children":[{"name":"a","children":[{"name":"img"}]},{"name":"div","children":[{"name":"p","children":[{"name":"a","children":[{"name":"data"}]},{"name":"data"},{"name":"a","children":[{"name":"data"}]}]},{"name":"p","children":[{"name":"a","children":[{"name":"data"}]},{"name":"data"},{"name":"a","children":[{"name":"data"}]}]}]}]}]},{"name":"div","children":[{"name":"div","children":[{"name":"div","children":[{"name":"a"},{"name":"a","children":[{"name":"data"}]},{"name":"div","children":[{"name":"a","children":[{"name":"data"}]},{"name":"data"},{"name":"a","children":[{"name":"data"}]}]},{"name":"div","children":[{"name":"ul","children":[{"name":"li","children":[{"name":"data"}]},{"name":"li","children":[{"name":"select","children":[{"name":"option","children":[{"name":"data"}]},{"name":"option","children":[{"name":"data"}]},{"name":"option","children":[{"name":"data"}]},{"name":"option","children":[{"name":"data"}]}]}]},{"name":"li","children":[{"name":"data"}]},{"name":"li","children":[{"name":"select","children":[{"name":"option","children":[{"name":"data"}]},{"name":"option","children":[{"name":"data"}]},{"name":"option","children":[{"name":"data"}]},{"name":"option","children":[{"name":"data"}]},{"name":"option","children":[{"name":"data"}]},{"name":"option","children":[{"name":"data"}]},{"name":"option","children":[{"name":"data"}]},{"name":"option","children":[{"name":"data"}]},{"name":"option","children":[{"name":"data"}]},{"name":"option","children":[{"name":"data"}]},{"name":"option","children":[{"name":"data"}]},{"name":"option","children":[{"name":"data"}]},{"name":"option","children":[{"name":"data"}]},{"name":"option","children":[{"name":"data"}]},{"name":"option","children":[{"name":"data"}]},{"name":"option","children":[{"name":"data"}]},{"name":"option","children":[{"name":"data"}]},{"name":"option","children":[{"name":"data"}]},{"name":"option","children":[{"name":"data"}]},{"name":"option","children":[{"name":"data"}]},{"name":"option","children":[{"name":"data"}]},{"name":"option","children":[{"name":"data"}]},{"name":"option","children":[{"name":"data"}]},{"name":"option","children":[{"name":"data"}]},{"name":"option","children":[{"name":"data"}]},{"name":"option","children":[{"name":"data"}]},{"name":"option","children":[{"name":"data"}]},{"name":"option","children":[{"name":"data"}]},{"name":"option","children":[{"name":"data"}]},{"name":"option","children":[{"name":"data"}]},{"name":"option","children":[{"name":"data"}]},{"name":"option","children":[{"name":"data"}]},{"name":"option","children":[{"name":"data"}]},{"name":"option","children":[{"name":"data"}]},{"name":"option","children":[{"name":"data"}]},{"name":"option","children":[{"name":"data"}]},{"name":"option","children":[{"name":"data"}]},{"name":"option","children":[{"name":"data"}]},{"name":"option","children":[{"name":"data"}]},{"name":"option","children":[{"name":"data"}]},{"name":"option","children":[{"name":"data"}]},{"name":"option","children":[{"name":"data"}]},{"name":"option","children":[{"name":"data"}]},{"name":"option","children":[{"name":"data"}]},{"name":"option","children":[{"name":"data"}]},{"name":"option","children":[{"name":"data"}]},{"name":"option","children":[{"name":"data"}]},{"name":"option","children":[{"name":"data"}]},{"name":"option","children":[{"name":"data"}]},{"name":"option","children":[{"name":"data"}]},{"name":"option","children":[{"name":"data"}]},{"name":"option","children":[{"name":"data"}]},{"name":"option","children":[{"name":"data"}]},{"name":"option","children":[{"name":"data"}]},{"name":"option","children":[{"name":"data"}]},{"name":"option","children":[{"name":"data"}]},{"name":"option","children":[{"name":"data"}]},{"name":"option","children":[{"name":"data"}]},{"name":"option","children":[{"name":"data"}]},{"name":"option","children":[{"name":"data"}]},{"name":"option","children":[{"name":"data"}]},{"name":"option","children":[{"name":"data"}]},{"name":"option","children":[{"name":"data"}]},{"name":"option","children":[{"name":"data"}]},{"name":"option","children":[{"name":"data"}]},{"name":"option","children":[{"name":"data"}]},{"name":"option","children":[{"name":"data"}]},{"name":"option","children":[{"name":"data"}]},{"name":"option","children":[{"name":"data"}]},{"name":"option","children":[{"name":"data"}]},{"name":"option","children":[{"name":"data"}]},{"name":"option","children":[{"name":"data"}]},{"name":"option","children":[{"name":"data"}]},{"name":"option","children":[{"name":"data"}]},{"name":"option","children":[{"name":"data"}]},{"name":"option","children":[{"name":"data"}]},{"name":"option","children":[{"name":"data"}]},{"name":"option","children":[{"name":"data"}]},{"name":"option","children":[{"name":"data"}]},{"name":"option","children":[{"name":"data"}]},{"name":"option","children":[{"name":"data"}]},{"name":"option","children":[{"name":"data"}]},{"name":"option","children":[{"name":"data"}]},{"name":"option","children":[{"name":"data"}]},{"name":"option","children":[{"name":"data"}]},{"name":"option","children":[{"name":"data"}]},{"name":"option","children":[{"name":"data"}]},{"name":"option","children":[{"name":"data"}]},{"name":"option","children":[{"name":"data"}]},{"name":"option","children":[{"name":"data"}]},{"name":"option","children":[{"name":"data"}]},{"name":"option","children":[{"name":"data"}]},{"name":"option","children":[{"name":"data"}]},{"name":"option","children":[{"name":"data"}]},{"name":"option","children":[{"name":"data"}]},{"name":"option","children":[{"name":"data"}]},{"name":"option","children":[{"name":"data"}]},{"name":"option","children":[{"name":"data"}]},{"name":"option","children":[{"name":"data"}]},{"name":"option","children":[{"name":"data"}]},{"name":"option","children":[{"name":"data"}]},{"name":"option","children":[{"name":"data"}]},{"name":"option","children":[{"name":"data"}]},{"name":"option","children":[{"name":"data"}]},{"name":"option","children":[{"name":"data"}]},{"name":"option","children":[{"name":"data"}]},{"name":"option","children":[{"name":"data"}]},{"name":"option","children":[{"name":"data"}]},{"name":"option","children":[{"name":"data"}]},{"name":"option","children":[{"name":"data"}]},{"name":"option","children":[{"name":"data"}]}]}]},{"name":"li","children":[{"name":"data"}]},{"name":"li","children":[{"name":"select","children":[{"name":"option","children":[{"name":"data"}]},{"name":"option","children":[{"name":"data"}]},{"name":"option","children":[{"name":"data"}]},{"name":"option","children":[{"name":"data"}]},{"name":"option","children":[{"name":"data"}]},{"name":"option","children":[{"name":"data"}]}]}]},{"name":"li","children":[{"name":"data"}]},{"name":"li","children":[{"name":"select","children":[{"name":"option","children":[{"name":"data"}]},{"name":"option","children":[{"name":"data"}]},{"name":"option","children":[{"name":"data"}]},{"name":"option","children":[{"name":"data"}]},{"name":"option","children":[{"name":"data"}]},{"name":"option","children":[{"name":"data"}]}]}]},{"name":"li","children":[{"name":"data"}]},{"name":"li","children":[{"name":"select","children":[{"name":"option","children":[{"name":"data"}]},{"name":"option","children":[{"name":"data"}]},{"name":"option","children":[{"name":"data"}]},{"name":"option","children":[{"name":"data"}]},{"name":"option","children":[{"name":"data"}]}]}]},{"name":"li","children":[{"name":"data"}]},{"name":"li","children":[{"name":"input"}]},{"name":"li","children":[{"name":"input"}]}]}]},{"name":"span"}]},{"name":"form"}]},{"name":"div","children":[{"name":"a","children":[{"name":"data"}]},{"name":"data"},{"name":"a","children":[{"name":"data"}]},{"name":"data"}]},{"name":"div","children":[{"name":"div","children":[{"name":"span"},{"name":"h4","children":[{"name":"data"}]},{"name":"span","children":[{"name":"data"},{"name":"img"},{"name":"img"},{"name":"img"},{"name":"img"},{"name":"img"}]},{"name":"input"},{"name":"span"},{"name":"table","children":[{"name":"tr","children":[{"name":"td","children":[{"name":"data"}]},{"name":"td","children":[{"name":"data"}]}]},{"name":"tr","children":[{"name":"td","children":[{"name":"data"}]},{"name":"td","children":[{"name":"data"}]},{"name":"td","children":[{"name":"data"}]},{"name":"td","children":[{"name":"data"}]}]},{"name":"tr","children":[{"name":"td","children":[{"name":"data"}]},{"name":"td","children":[{"name":"data"}]},{"name":"td","children":[{"name":"data"}]},{"name":"td","children":[{"name":"data"}]}]},{"name":"tr","children":[{"name":"td","children":[{"name":"data"}]},{"name":"td","children":[{"name":"data"}]},{"name":"td","children":[{"name":"data"}]},{"name":"td","children":[{"name":"data"}]}]},{"name":"tr","children":[{"name":"td","children":[{"name":"data"}]},{"name":"td","children":[{"name":"data"}]},{"name":"td","children":[{"name":"data"}]},{"name":"td","children":[{"name":"data"}]}]},{"name":"tr","children":[{"name":"td","children":[{"name":"data"}]},{"name":"td","children":[{"name":"data"}]},{"name":"td","children":[{"name":"data"}]},{"name":"td","children":[{"name":"data"}]}]},{"name":"tr","children":[{"name":"td","children":[{"name":"data"}]},{"name":"td","children":[{"name":"data"}]},{"name":"td","children":[{"name":"data"}]},{"name":"td","children":[{"name":"data"}]}]},{"name":"tr","children":[{"name":"td","children":[{"name":"data"}]},{"name":"td","children":[{"name":"data"}]},{"name":"td","children":[{"name":"data"}]},{"name":"td","children":[{"name":"data"}]}]},{"name":"tr","children":[{"name":"td","children":[{"name":"data"}]},{"name":"td","children":[{"name":"data"}]},{"name":"td","children":[{"name":"data"}]},{"name":"td"}]},{"name":"tr","children":[{"name":"td","children":[{"name":"data"}]},{"name":"td","children":[{"name":"data"}]}]},{"name":"tr","children":[{"name":"td","children":[{"name":"data"}]},{"name":"td","children":[{"name":"data"}]}]},{"name":"tr","children":[{"name":"td","children":[{"name":"data"}]},{"name":"td","children":[{"name":"p","children":[{"name":"data"}]}]}]}]},{"name":"table","children":[{"name":"tr"}]},{"name":"span"},{"name":"div","children":[{"name":"ul","children":[{"name":"li","children":[{"name":"data"}]},{"name":"li","children":[{"name":"a"},{"name":"em"}]},{"name":"li","children":[{"name":"a"},{"name":"em"}]},{"name":"li","children":[{"name":"a"},{"name":"em"}]},{"name":"li","children":[{"name":"a"},{"name":"em"}]},{"name":"li","children":[{"name":"a"},{"name":"em"}]},{"name":"li","children":[{"name":"a"},{"name":"em"}]},{"name":"li","children":[{"name":"a"},{"name":"em"}]},{"name":"li","children":[{"name":"a"},{"name":"em"}]}]}]},{"name":"span"},{"name":"div","children":[{"name":"data"},{"name":"font","children":[{"name":"data"}]},{"name":"data"}]},{"name":"span"}]}]},{"name":"div","children":[{"name":"div","children":[{"name":"h4","children":[{"name":"data"}]},{"name":"div","children":[{"name":"p","children":[{"name":"img"}]},{"name":"p","children":[{"name":"data"}]}]}]},{"name":"span"},{"name":"div","children":[{"name":"div","children":[{"name":"h4","children":[{"name":"data"}]},{"name":"span","children":[{"name":"a","children":[{"name":"data"}]}]}]},{"name":"ul","children":[{"name":"li","children":[{"name":"span","children":[{"name":"img"},{"name":"img"},{"name":"img"},{"name":"img"},{"name":"img"}]},{"name":"a","children":[{"name":"data"}]}]},{"name":"li","children":[{"name":"span","children":[{"name":"img"},{"name":"img"},{"name":"img"},{"name":"img"},{"name":"img"}]},{"name":"a","children":[{"name":"data"}]}]},{"name":"li","children":[{"name":"span","children":[{"name":"img"},{"name":"img"},{"name":"img"},{"name":"img"},{"name":"img"}]},{"name":"a","children":[{"name":"data"}]}]},{"name":"li","children":[{"name":"span","children":[{"name":"img"},{"name":"img"},{"name":"img"},{"name":"img"},{"name":"img"}]},{"name":"a","children":[{"name":"data"}]}]},{"name":"li","children":[{"name":"span","children":[{"name":"img"},{"name":"img"},{"name":"img"},{"name":"img"},{"name":"img"}]},{"name":"a","children":[{"name":"data"}]}]},{"name":"li","children":[{"name":"span","children":[{"name":"img"},{"name":"img"},{"name":"img"},{"name":"img"},{"name":"img"}]},{"name":"a","children":[{"name":"data"}]}]}]}]},{"name":"span"},{"name":"div","children":[{"name":"div","children":[{"name":"h4","children":[{"name":"data"}]},{"name":"span","children":[{"name":"a","children":[{"name":"data"}]}]}]},{"name":"ul","children":[{"name":"li","children":[{"name":"a","children":[{"name":"data"}]}]},{"name":"li","children":[{"name":"a","children":[{"name":"data"}]}]},{"name":"li","children":[{"name":"a","children":[{"name":"data"}]}]},{"name":"li","children":[{"name":"a","children":[{"name":"data"}]}]},{"name":"li","children":[{"name":"a","children":[{"name":"data"}]}]},{"name":"li","children":[{"name":"a","children":[{"name":"data"}]}]},{"name":"li","children":[{"name":"a","children":[{"name":"data"}]}]},{"name":"li","children":[{"name":"a","children":[{"name":"data"}]}]}]}]}]},{"name":"span"},{"name":"span"},{"name":"span"},{"name":"span"}]}]}]}
